README.md
setup.py
thbase/__init__.py
thbase/clientbase.py
thbase/config.py
thbase/connection.py
thbase.egg-info/PKG-INFO
thbase.egg-info/SOURCES.txt
thbase.egg-info/dependency_links.txt
thbase.egg-info/requires.txt
thbase.egg-info/top_level.txt
thbase/hbase/THBaseService.py
thbase/hbase/__init__.py
thbase/hbase/constants.py
thbase/hbase/ttypes.py
thbase/thrift2/__init__.py
thbase/thrift2/cell.py
thbase/thrift2/client.py
thbase/thrift2/operation.py
thbase/thrift2/table.py
thbase/util/__init__.py
thbase/util/builder.py
thbase/util/bytes.py
thbase/util/executor.py
thbase/util/handlers.py
thbase/util/login.py