Metadata-Version: 2.1
Name: thbase
Version: 1.3.7
Summary: HBase thrift2 client python API. Compatible with python2.7 and python3
Home-page: https://github.com/YutSean
Author: Yutong Sean
Author-email: yutongsean@gmail.com
License: UNKNOWN
Platform: UNKNOWN
Classifier: License :: OSI Approved :: Apache Software License
Classifier: Natural Language :: English
Classifier: Programming Language :: Python :: 2.7
Classifier: Programming Language :: Python :: 3
